solution_efe_client_security/__init__.py
solution_efe_client_security/securityGuard.py
solution_efe_client_security/securityService.py
solution_efe_client_security-1.0.2.dist-info/METADATA
solution_efe_client_security-1.0.2.dist-info/WHEEL
solution_efe_client_security-1.0.2.dist-info/top_level.txt
solution_efe_client_security-1.0.2.dist-info/RECORD
